graffo/__init__.py
graffo/client.py
graffo/collections/__init__.py
graffo/collections/client.py
graffo/collections/raw_client.py
graffo/collections/types/__init__.py
graffo/collections/types/search_collections_readable_id_search_post_request_body.py
graffo/collections/types/search_collections_readable_id_search_post_response.py
graffo/core/__init__.py
graffo/core/api_error.py
graffo/core/client_wrapper.py
graffo/core/datetime_utils.py
graffo/core/file.py
graffo/core/force_multipart.py
graffo/core/http_client.py
graffo/core/http_response.py
graffo/core/jsonable_encoder.py
graffo/core/pydantic_utilities.py
graffo/core/query_encoder.py
graffo/core/remove_none_from_dict.py
graffo/core/request_options.py
graffo/core/serialization.py
graffo/environment.py
graffo/errors/__init__.py
graffo/errors/unprocessable_entity_error.py
graffo/py.typed
graffo/source_connections/__init__.py
graffo/source_connections/client.py
graffo/source_connections/raw_client.py
graffo/source_connections/types/__init__.py
graffo/source_connections/types/source_connection_create_authentication.py
graffo/source_connections/types/source_connection_update_authentication.py
graffo/sources/__init__.py
graffo/sources/client.py
graffo/sources/raw_client.py
graffo/types/__init__.py
graffo/types/action_check_request.py
graffo/types/action_check_response.py
graffo/types/agent_api_key.py
graffo/types/agent_api_key_cluster_management.py
graffo/types/agent_api_key_collection_stats.py
graffo/types/agent_api_key_create.py
graffo/types/agent_api_key_revoke.py
graffo/types/agent_api_key_status.py
graffo/types/agent_api_key_summary.py
graffo/types/agent_api_key_update.py
graffo/types/agent_api_key_with_clusters.py
graffo/types/agent_api_key_with_full_key.py
graffo/types/api_key.py
graffo/types/api_key_create.py
graffo/types/audit_action_type.py
graffo/types/audit_log.py
graffo/types/audit_log_category.py
graffo/types/audit_log_level.py
graffo/types/audit_log_search_result.py
graffo/types/auth_provider.py
graffo_sdk-0.1.54.dist-info/METADATA
graffo_sdk-0.1.54.dist-info/WHEEL
graffo_sdk-0.1.54.dist-info/RECORD
